Metadata-Version: 1.0
Name: nekos.py
Version: 1.0.1
Summary: A Python module that uses Nekos API
Home-page: https://github.com/Nekos-life/nekos.py
Author: AlexFlipnote
Author-email: UNKNOWN
License: GNU v3
Platform: UNKNOWN
